manta_client/__init__.py
manta_client/__main__.py
manta_client/env.py
manta_client/jupyter.py
manta_client/util.py
manta_client/api/__init__.py
manta_client/api/api.py
manta_client/api/client.py
manta_client/base/__init__.py
manta_client/base/config.py
manta_client/base/filenames.py
manta_client/base/git_repo.py
manta_client/base/packet.py
manta_client/base/settings.py
manta_client/cli/__init__.py
manta_client/cli/cli_artifact.py
manta_client/cli/entry.py
manta_client/cli/utils.py
manta_client/errors/__init__.py
manta_client/errors/term.py
manta_client/errors/usages.py
manta_client/tracking/__init__.py
manta_client/tuning/__init__.py
manta_client/tuning/manta_tune.py
manta_client/tuning/tune_agent.py
manta_client/tuning/tune_controller.py
manta_client/tuning/interface/__init__.py
manta_client/tuning/interface/agent.py
manta_client/tuning/interface/controller.py
manta_client/tuning/interface/parameter.py
manta_client/tuning/internal/__init__.py
manta_client/tuning/internal/controller.py
manta_client/tuning/internal/heartbeat.py
manta_client/tuning/internal/agents/__init__.py
manta_client/tuning/internal/agents/function_agent.py
manta_client/tuning/internal/agents/program_agent.py
manta_client/tuning/internal/integrations/__init__.py
manta_client/tuning/internal/integrations/control_bayesian.py
manta_client/tuning/internal/integrations/control_chocolate.py
manta_client/tuning/internal/integrations/control_hyperband.py
manta_client/tuning/internal/integrations/control_hyperopt.py
manta_client/tuning/internal/integrations/control_optuna.py
manta_client/tuning/internal/integrations/control_ray.py
manta_client/tuning/internal/integrations/control_sklearn.py
manta_lab/__init__.py
manta_lab/__main__.py
manta_lab/env.py
manta_lab/jupyter.py
manta_lab/util.py
manta_lab/api/__init__.py
manta_lab/api/api.py
manta_lab/api/client.py
manta_lab/assets/words/adjectives/age.txt
manta_lab/assets/words/adjectives/algorithms.txt
manta_lab/assets/words/adjectives/appearance.txt
manta_lab-0.1.2.dev0.dist-info/LICENSE
manta_lab-0.1.2.dev0.dist-info/METADATA
manta_lab-0.1.2.dev0.dist-info/WHEEL
manta_lab-0.1.2.dev0.dist-info/entry_points.txt
manta_lab-0.1.2.dev0.dist-info/top_level.txt
manta_lab-0.1.2.dev0.dist-info/RECORD
